dear_ros_node_viewer/__init__.py
dear_ros_node_viewer/__main__.py
dear_ros_node_viewer/_version.py
dear_ros_node_viewer/caret2networkx.py
dear_ros_node_viewer/caret_extend_callback_group.py
dear_ros_node_viewer/caret_extend_path.py
dear_ros_node_viewer/dear_ros_node_viewer.py
dear_ros_node_viewer/dot2networkx.py
dear_ros_node_viewer/graph_layout.py
dear_ros_node_viewer/graph_manager.py
dear_ros_node_viewer/graph_view.py
dear_ros_node_viewer/graph_viewmodel.py
dear_ros_node_viewer/logger_factory.py
dear_ros_node_viewer/mermaid_exporter.py
dear_ros_node_viewer/ros2networkx.py
dear_ros_node_viewer/setting.json
dear_ros_node_viewer/version_dummy.py
dear_ros_node_viewer/font/roboto/Roboto-Medium.ttf
dear_ros_node_viewer-1.1.2.dist-info/licenses/LICENSE
dear_ros_node_viewer-1.1.2.dist-info/METADATA
dear_ros_node_viewer-1.1.2.dist-info/WHEEL
dear_ros_node_viewer-1.1.2.dist-info/entry_points.txt
dear_ros_node_viewer-1.1.2.dist-info/top_level.txt
dear_ros_node_viewer-1.1.2.dist-info/RECORD
