Metadata-Version: 2.4
Name: dear_ros_node_viewer
Version: 1.1.2
Summary: dear_ros_node_viewer
Author-email: iwatake2222 <take.iwiw2222@gmail.com>
Maintainer-email: iwatake2222 <take.iwiw2222@gmail.com>
Project-URL: Homepage, https://github.com/iwatake2222/dear_ros_node_viewer
Project-URL: Bug Reports, https://github.com/iwatake2222/dear_ros_node_viewer/issues
Project-URL: Source, https://github.com/iwatake2222/dear_ros_node_viewer
Keywords: ros,ros2,tool,rqt_graph,dearpygui,node-editor
Classifier: Development Status :: 5 - Production/Stable
Classifier: Intended Audience :: Developers
Classifier: Topic :: Utilities
Classifier: Topic :: Scientific/Engineering :: Visualization
Classifier: Framework :: Robot Framework :: Tool
Classifier: License :: OSI Approved :: Apache Software License
Classifier: Programming Language :: Python :: 3
Classifier: Programming Language :: Python :: 3.7
Classifier: Programming Language :: Python :: 3.8
Classifier: Programming Language :: Python :: 3.9
Classifier: Programming Language :: Python :: 3.10
Classifier: Programming Language :: Python :: 3.11
Classifier: Programming Language :: Python :: 3 :: Only
Requires-Python: >=3.7
License-File: LICENSE
Requires-Dist: dearpygui>=1.10.1
Requires-Dist: matplotlib
Requires-Dist: networkx>=3.0
Requires-Dist: networkx-mermaid
Requires-Dist: numpy
Requires-Dist: pydot<4.0.0,>=3.0
Requires-Dist: pyyaml
Provides-Extra: dev
Requires-Dist: check-manifest; extra == "dev"
Provides-Extra: test
Requires-Dist: coverage; extra == "test"
Dynamic: license-file
